README.rst
setup.py
src/waldur_digitalocean/__init__.py
src/waldur_digitalocean/admin.py
src/waldur_digitalocean/apps.py
src/waldur_digitalocean/backend.py
src/waldur_digitalocean/cost_tracking.py
src/waldur_digitalocean/executors.py
src/waldur_digitalocean/extension.py
src/waldur_digitalocean/filters.py
src/waldur_digitalocean/handlers.py
src/waldur_digitalocean/log.py
src/waldur_digitalocean/models.py
src/waldur_digitalocean/serializers.py
src/waldur_digitalocean/tasks.py
src/waldur_digitalocean/urls.py
src/waldur_digitalocean/views.py
src/waldur_digitalocean.egg-info/PKG-INFO
src/waldur_digitalocean.egg-info/SOURCES.txt
src/waldur_digitalocean.egg-info/dependency_links.txt
src/waldur_digitalocean.egg-info/entry_points.txt
src/waldur_digitalocean.egg-info/not-zip-safe
src/waldur_digitalocean.egg-info/requires.txt
src/waldur_digitalocean.egg-info/top_level.txt
src/waldur_digitalocean/migrations/0001_initial.py
src/waldur_digitalocean/migrations/__init__.py