Metadata-Version: 2.1
Name: waldur-digitalocean
Version: 0.11.0
Summary: Waldur plugin for managing DigitalOcean resources.
Home-page: http://waldur.com
Author: OpenNode Team
Author-email: info@opennodecloud.com
License: MIT
Platform: UNKNOWN
Classifier: Framework :: Django
Classifier: Intended Audience :: Developers
Classifier: Intended Audience :: System Administrators
Classifier: License :: OSI Approved :: MIT License
Classifier: Operating System :: OS Independent
Provides-Extra: tests
Provides-Extra: dev
